.gitlab-ci.yml
README.md
lbciagentInstaller.sh
lbciagentdemon.sh
setup.py
bin/lbciagent
lbciagent/DeploymentPolicy.py
lbciagent/LbCIAgent.py
lbciagent/__init__.py
lbciagent/slotsOnCVMFS
lbciagent.egg-info/PKG-INFO
lbciagent.egg-info/SOURCES.txt
lbciagent.egg-info/dependency_links.txt
lbciagent.egg-info/requires.txt
lbciagent.egg-info/top_level.txt
lbciagent/scripts/checkDeploymentPolicy.py
lbciagent/test/__init__.py
lbciagent/test/testCases.json
lbciagent/test/test_order.py